rxbus/__init__.py
rxbus/core/RxBus.py
rxbus/core/__init__.py
rxbus/test/__init__.py
rxbus/test/test.py
rxbus-0.1.2.dist-info/LICENSE
rxbus-0.1.2.dist-info/METADATA
rxbus-0.1.2.dist-info/WHEEL
rxbus-0.1.2.dist-info/top_level.txt
rxbus-0.1.2.dist-info/RECORD
