Metadata-Version: 2.1
Name: rxbus
Version: 0.1.2
Summary: 基于rxpy 实现的RxBus
Home-page: https://gitee.com/osczaizai/RxBus.git
Author: Anjie Guan
Author-email: angelswy163@163.com
License: MIT
Platform: UNKNOWN
Classifier: License :: OSI Approved :: MIT License
Classifier: Programming Language :: Python
Classifier: Programming Language :: Python :: 3
Classifier: Programming Language :: Python :: 3.6
Classifier: Programming Language :: Python :: Implementation :: CPython
Classifier: Programming Language :: Python :: Implementation :: PyPy
Requires-Python: >=3.6.0
Requires-Dist: rx (>=3.0.1)
